{
	"configurations" : 
	[
		{
			"directories" : 
			[
				{
					"build" : ".",
					"minimumCMakeVersion" : 
					{
						"string" : "3.8"
					},
					"projectIndex" : 0,
					"source" : ".",
					"targetIndexes" : 
					[
						0
					]
				}
			],
			"name" : "Debug",
			"projects" : 
			[
				{
					"directoryIndexes" : 
					[
						0
					],
					"name" : "P1",
					"targetIndexes" : 
					[
						0
					]
				}
			],
			"targets" : 
			[
				{
					"directoryIndex" : 0,
					"id" : "P1::@6890427a1f51a3e7e1df",
					"jsonFile" : "target-P1-Debug-3aa08d883bb4c500b2c4.json",
					"name" : "P1",
					"projectIndex" : 0
				}
			]
		}
	],
	"kind" : "codemodel",
	"paths" : 
	{
		"build" : "C:/Users/ADMIN/source/repos/Fix-er/Project1/out/build/x64-Debug (default)",
		"source" : "C:/Users/ADMIN/source/repos/Fix-er/Project1"
	},
	"version" : 
	{
		"major" : 2,
		"minor" : 1
	}
}
